{
  "code": 0,
  "msg": "",
  "count": 30,
  "data": [
    {
      "class_id": "1",
      "class_name": "PHP",
      "describe": "PHP相关的文章",
      "status": 1,
      "create_time": "2016-12-14 05:05:05"
    },  
     {
      "class_id": "2",
      "class_name": "PHP",
      "describe": "PHP相关的文章",
      "status": 0,
      "create_time": "2016-12-14 05:05:05"
    },   
    {
      "class_id": "3",
      "class_name": "PHP",
      "describe": "PHP相关的文章",
      "status": 1,
      "create_time": "2016-12-14 05:05:05"
    },   
    {
      "class_id": "4",
      "class_name": "PHP",
      "describe": "PHP相关的文章",
      "status": 0,
      "create_time": "2016-12-14 05:05:05"
    },   
    {
      "class_id": "5",
      "class_name": "PHP",
      "describe": "PHP相关的文章",
      "status": 1,
      "create_time": "2016-12-14 05:05:05"
    },   
    {
      "class_id": "6",
      "class_name": "PHP",
      "describe": "PHP相关的文章",
      "status": 0,
      "create_time": "2016-12-14 05:05:05"
    } 
  ]
}

